asfa/__init__.py
asfa/_config.py
asfa/connection.py
asfa-1.1.1.dist-info/METADATA
asfa-1.1.1.dist-info/WHEEL
asfa-1.1.1.dist-info/top_level.txt
asfa-1.1.1.dist-info/RECORD
