Metadata-Version: 2.4
Name: asfa
Version: 1.1.1
Classifier: Programming Language :: Python :: 3
Classifier: License :: OSI Approved :: MIT License
Classifier: Operating System :: OS Independent
Requires-Python: >=3.6
Requires-Dist: anyio==4.9.0
Requires-Dist: certifi==2025.1.31
Requires-Dist: dotenv==0.9.9
Requires-Dist: h11==0.14.0
Requires-Dist: httpcore==1.0.8
Requires-Dist: httpx==0.28.1
Requires-Dist: idna==3.10
Requires-Dist: python-dotenv==1.1.0
Requires-Dist: setuptools==78.1.0
Requires-Dist: sniffio==1.3.1
Dynamic: classifier
Dynamic: description
Dynamic: description-content-type
Dynamic: requires-dist
Dynamic: requires-python
